kitcoda/__init__.py
kitcoda/kitcoda.py
kitcoda-1.0.1.dist-info/METADATA
kitcoda-1.0.1.dist-info/WHEEL
kitcoda-1.0.1.dist-info/entry_points.txt
kitcoda-1.0.1.dist-info/top_level.txt
kitcoda-1.0.1.dist-info/RECORD
