Metadata-Version: 2.4
Name: kitcoda
Version: 1.0.1
Summary: An esolang where every keyword is based on cats and kittens
Requires-Python: >=3.10
Provides-Extra: dev
Requires-Dist: pytest>=8.4.1; extra == "dev"
